dosip/__init__.py
dosip/buffer.py
dosip/core.py
dosip/simulation.py
dosip/singleton.py
dosip/tests/__init__.py
dosip/tests/test_core.py
PyDOSIP-1.0.0.dist-info/LICENSE
PyDOSIP-1.0.0.dist-info/METADATA
PyDOSIP-1.0.0.dist-info/WHEEL
PyDOSIP-1.0.0.dist-info/top_level.txt
PyDOSIP-1.0.0.dist-info/RECORD
