Metadata-Version: 2.1
Name: PyDOSIP
Version: 1.0.0
Summary: A python library to detect operating states in industrial process
Home-page: https://github.com/know-ai/PyDOSIP
Author: KnowAI
Author-email: dev.know.ai@gmail.com
License: MIT License
Platform: UNKNOWN
Classifier: Programming Language :: Python :: 3.8
Classifier: Programming Language :: Python :: 3.9
Classifier: Programming Language :: Python :: 3.10
Classifier: Programming Language :: Python :: 3.11
Classifier: Programming Language :: Python :: 3.12
Classifier: License :: OSI Approved :: MIT License
Classifier: Operating System :: OS Independent
Classifier: Topic :: Software Development :: Libraries
Classifier: Topic :: System :: Monitoring
License-File: LICENSE
Requires-Dist: PyYAML==6.0.2
Requires-Dist: flake8>=6.0.0
Requires-Dist: matplotlib>=3.7.0
Requires-Dist: numpy>=1.24.0
Requires-Dist: pytest>=7.0.0
